Metadata-Version: 2.1
Name: lyrah-classinstance
Version: 0.0.1
Summary: A class instance
Home-page: UNKNOWN
Author: Yorushika Lyrah
Author-email: lyrahprivacy@gmail.com
License: MIT
Keywords: Class
Platform: UNKNOWN
Classifier: Development Status :: 5 - Production/Stable
Classifier: Intended Audience :: Education
Classifier: Operating System :: Microsoft :: Windows :: Windows 10
Classifier: License :: OSI Approved :: MIT License
Classifier: Programming Language :: Python :: 3
